[
    {
        "transactionName": "Main_page",
        "rawStartTime": 1631353769160,
        "rawEndTime": 1631353769515
    },
    {
        "transactionName": "login",
        "rawStartTime": 1631353769560,
        "rawEndTime": 1631353769925
    },
    {
        "transactionName": "flights",
        "rawStartTime": 1631353769960,
        "rawEndTime": 1631353770439
    },
    {
        "transactionName": "find_flight",
        "rawStartTime": 1631353770472,
        "rawEndTime": 1631353770818
    },
    {
        "transactionName": "choose_ticket",
        "rawStartTime": 1631353770840,
        "rawEndTime": 1631353771144
    },
    {
        "transactionName": "payment_details",
        "rawStartTime": 1631353771180,
        "rawEndTime": 1631353771494
    },
    {
        "transactionName": "sign_off",
        "rawStartTime": 1631353771520,
        "rawEndTime": 1631353771850
    },
    {
        "transactionName": "UC_03_Buy_ticket",
        "rawStartTime": 1631353769138,
        "rawEndTime": 1631353771860
    }
]