[
    {
        "transactionName": "Main_page",
        "rawStartTime": 1631353740490,
        "rawEndTime": 1631353740794
    },
    {
        "transactionName": "login",
        "rawStartTime": 1631353740830,
        "rawEndTime": 1631353741128
    },
    {
        "transactionName": "flights",
        "rawStartTime": 1631353741150,
        "rawEndTime": 1631353741487
    },
    {
        "transactionName": "find_flight",
        "rawStartTime": 1631353741520,
        "rawEndTime": 1631353741806
    },
    {
        "transactionName": "choose_ticket",
        "rawStartTime": 1631353741840,
        "rawEndTime": 1631353742084
    },
    {
        "transactionName": "payment_details",
        "rawStartTime": 1631353742107,
        "rawEndTime": 1631353742351
    },
    {
        "transactionName": "sign_off",
        "rawStartTime": 1631353742390,
        "rawEndTime": 1631353742657
    },
    {
        "transactionName": "UC_03_Buy_ticket",
        "rawStartTime": 1631353740470,
        "rawEndTime": 1631353742670
    }
]